src/__init__.py
src/constants.py
src/migrate.py
tests/__init__.py
tests/test_migratedatabase.py
pymigratedb-1.3.0.dist-info/LICENSE.txt
pymigratedb-1.3.0.dist-info/METADATA
pymigratedb-1.3.0.dist-info/WHEEL
pymigratedb-1.3.0.dist-info/entry_points.txt
pymigratedb-1.3.0.dist-info/top_level.txt
pymigratedb-1.3.0.dist-info/RECORD
