Metadata-Version: 2.1
Name: pymigratedb
Version: 1.3.0
Summary: This is a package to help you to migrate your database. It will be useful when you work on frameworks or programming languages that don't have a built-in tool to do it or it's little hard to setup.
Home-page: https://github.com/INDICO-INNOVATION/py-migrate-db
Author: Indico Innovation
Author-email: dev@indicoinnovation.pt
License: Apache License
Keywords: migrate,migration,database,db
Classifier: Development Status :: 3 - Alpha
Classifier: Intended Audience :: Developers
Classifier: Programming Language :: Python :: 3
Requires-Python: >=3.6
License-File: LICENSE.txt
Requires-Dist: greenlet (==1.1.2)
Requires-Dist: psycopg2-binary (==2.9.3)
Requires-Dist: python-dotenv (==0.19.2)
Requires-Dist: SQLAlchemy (==1.4.31)
